daphne/__init__.py
daphne/__main__.py
daphne/access.py
daphne/cli.py
daphne/endpoints.py
daphne/http_protocol.py
daphne/server.py
daphne/testing.py
daphne/utils.py
daphne/ws_protocol.py
twisted/plugins/fd_endpoint.py
ocp_daphne-1.1.1.dist-info/LICENSE
ocp_daphne-1.1.1.dist-info/METADATA
ocp_daphne-1.1.1.dist-info/WHEEL
ocp_daphne-1.1.1.dist-info/entry_points.txt
ocp_daphne-1.1.1.dist-info/top_level.txt
ocp_daphne-1.1.1.dist-info/RECORD
