Metadata-Version: 2.1
Name: ocp-daphne
Version: 1.1.1
Summary: Django ASGI (HTTP/WebSocket) server
Home-page: UNKNOWN
Author: Aryan Kapoor
Author-email: pro.akapoor@gmail.com
License: BSD
Platform: UNKNOWN
Classifier: Development Status :: 4 - Beta
Classifier: Environment :: Web Environment
Classifier: Intended Audience :: Developers
Classifier: License :: OSI Approved :: BSD License
Classifier: Operating System :: OS Independent
Classifier: Programming Language :: Python
Classifier: Programming Language :: Python :: 3
Classifier: Programming Language :: Python :: 3.6
Classifier: Programming Language :: Python :: 3.7
Classifier: Programming Language :: Python :: 3.8
Classifier: Programming Language :: Python :: 3.9
Classifier: Topic :: Internet :: WWW/HTTP
Requires-Python: >=3.6
License-File: LICENSE
Requires-Dist: twisted[tls] (>=18.7)
Requires-Dist: autobahn (>=0.18)
Requires-Dist: asgiref (<4,>=3.2.10)
Provides-Extra: tests
Requires-Dist: hypothesis (==4.23) ; extra == 'tests'
Requires-Dist: pytest (~=3.10) ; extra == 'tests'
Requires-Dist: pytest-asyncio (~=0.8) ; extra == 'tests'
